MyMathFun/__init__.py
MyMathFun/code.py
MyMathFun-1.0.2.dist-info/LICENSE
MyMathFun-1.0.2.dist-info/METADATA
MyMathFun-1.0.2.dist-info/WHEEL
MyMathFun-1.0.2.dist-info/top_level.txt
MyMathFun-1.0.2.dist-info/RECORD
